sinnercore/__init__.py
sinnercore/amarterasu.py
sinnercore/sinnercore.py
sinnercore/sqlgre.py
sinnercore/tsukuyomi.py
sinnercore-5.6.9.dist-info/LICENSE
sinnercore-5.6.9.dist-info/METADATA
sinnercore-5.6.9.dist-info/WHEEL
sinnercore-5.6.9.dist-info/top_level.txt
sinnercore-5.6.9.dist-info/RECORD
