Metadata-Version: 2.1
Name: sinnercore
Version: 5.6.9
Summary: A Powerful And Advance Telegram Bot By Sinner Murphy. Latest Version As Of 05 March 2025. Fantastic Package With Awesome Features.
Home-page: https://github.com/yourgithub/SinnerMurphy
Author: Sinner Murphy
Author-email: sinnermurphy@hi2.in
License: MIT
Classifier: Programming Language :: Python :: 3
Classifier: License :: OSI Approved :: MIT License
Classifier: Operating System :: OS Independent
Requires-Python: >=3.7
License-File: LICENSE
Requires-Dist: telethon
Requires-Dist: sqlalchemy
Requires-Dist: pg8000
Requires-Dist: googletrans==4.0.0-rc1
Requires-Dist: google
Requires-Dist: instaloader
Requires-Dist: requests
Requires-Dist: emoji
Requires-Dist: gtts
Requires-Dist: pytz
